betterspread/__init__.py
betterspread/cell.py
betterspread/connection.py
betterspread/row.py
betterspread/sheet.py
betterspread/style.py
betterspread/tab.py
betterspread/utils.py
betterspread-0.2.2.dist-info/METADATA
betterspread-0.2.2.dist-info/WHEEL
betterspread-0.2.2.dist-info/RECORD
