Metadata-Version: 2.1
Name: betterspread
Version: 0.2.2
Summary: 
License: MIT
Author: Md Shahriyar Alam
Author-email: contact@shahriyar.dev
Requires-Python: >=3.9,<4.0
Classifier: License :: OSI Approved :: MIT License
Classifier: Programming Language :: Python :: 3
Classifier: Programming Language :: Python :: 3.9
Classifier: Programming Language :: Python :: 3.10
Classifier: Programming Language :: Python :: 3.11
Classifier: Programming Language :: Python :: 3.12
Requires-Dist: gspread (>=6.1.0,<7.0.0)
Requires-Dist: gspread-formatting (>=1.1.2,<2.0.0)
Project-URL: Bug Tracker, https://github.com/shahriyardx/betterspread/issues
Project-URL: homepage, https://github.com/shahriyardx/betterspread
Project-URL: repository, https://github.com/shahriyardx/betterspread
